Workbook

Sheet Kangatang

Sheet General
A2: Project: | D2: Exchange Rate: | E2: =Import!AH13 -> 27000
A4: No | B4: Desription | C4: Quanity | D4: Unit Price | E4: Total
A5: 1 | B5: Sheet A | C5: 1 | D5: =E2*Import!X15 -> 337058010 | E5: =D5*C5 -> 337058010
A6: 2 | B6: Sheet B | C6: 1 | E6: =D6*C6 -> 0
A7: 3 | B7: Prelim Estimation | C7: 1 | D7: 5000000 | E7: =D7*C7 -> 5000000
B9: TOTAL COST | E9: =SUM(E5:E7) -> 342058010
B10: TOTAL REVENUE | E10: =(Import!AH14*Import!E14+Import!#REF!*Import!#REF!) -> #REF!
B11: GENERAL GP | E11: =(E10-E9)/E10 -> #REF!

Sheet Import
B1: COSTING SHEET | E1: HAULAGE + CO fee | G1: FREIGHT | Q1: LOCAL | V1: 25000
B2: PROJECT: ABC | D2: 1.3 | E2: LCL | F2: 350 | G2: =E2 -> LCL | H2: =50*5 -> 250 | I2: =F2+H2+T2 -> 770 | J2: =800+800+350 -> 1950 | Q2: =G2 -> LCL | R2: =SUM(T2:T7) -> 500 | S2: Local charge | T2: 170 | U2: =(5+15+5)*F5+60 -> 167.5
E3: FLAT FEE | F3: 0 | G3: FLAT FEE | H3: 0 | Q3: FLAT FEE | R3: 0 | S3: Clearance | T3: 70
B4: DATE: | C4: =NOW() -> 46304.463 | E4: RATE/CBM | F4: 0 | G4: RATE/CBM | H4: 0 | Q4: RATE/CBM | R4: 0 | S4: Load / Install | T4: 100 | V4: =1500000+10000*10 -> 1600000 | W4: =V4/25000 -> 64
E5: TOTAL CBM | F5: =K15 -> 4.3 | G5: TOTAL CBM | H5: =K15 -> 4.3 | Q5: TOTAL CBM | R5: =K15 -> 4.3 | S5: Deliver | T5: 100 | U5: =1200000*2 -> 2400000 | V5: =U5/25000 -> 96
B6: CURRENCY: | C6: USD | E6: TOTAL CHARGE | F6: =IF(ROUND(F4*F5,2)>F2,ROUND(F4*F5,2)+F3,F2+F3) -> 350 | G6: TOTAL CHARGE | H6: =IF(ROUND(H4*H5,2)>H2,ROUND(H4*H5,2)+H3,H2+H3) -> 250 | Q6: TOTAL CHARGE | R6: =IF(ROUND(R4*R5,2)>R2,ROUND(R4*R5,2)+R3,R2+R3+(R4*R5)) -> 500 | S6: Warehouse | T6: 30
B7: EXCHANGE RATE: | C7: 1 | E7: COST/CBM | F7: =IF(F5>0,ROUND(F6/F5,2),0) -> 81.4 | G7: COST/CBM | H7: =IF(H5>0,ROUND(H6/H5,2),0) -> 58.14 | Q7: COST/CBM | R7: =IF(R5>0,ROUND(R6/R5,2),0) -> 116.28 | S7: Prelim | T7: 30
I8: RATE ON CNF | T8: DRIVEN MARGIN
B9: SUPPLIER: | C9: HUMANSCALE | I9: 0.0075 | T9: 0.4
B10: DELIVERY TERMS OF PURCHASES | C10: EXW China
B11: DELIVERY TERMS OF SALES | C11: D2D HCM / HN | I11: =$I$14*$AH$13 -> 28965600 | J11: =I11*2 -> 57931200 | K11: =I11*2.5 -> 72414000 | P11: =$I$14*$AH$13*2.5 -> 72414000 | Q11: =$I$14*$AH$13*3 -> 86896800 | Y11: DRIVEN MARGIN METHOD | AB11: DRIVEN MARKET METHOD | AF11: CAF
B12: DESCRIPTION | C12: IMAGE | D12: DIM (CBM) | E12: QTY | F12: FOB UNIT COST | G12: CONVERTED UNIT COST (USD) | H12: % discounted | I12: DISCOUNTED FOB | J12: TTL FOB | K12: TTL DIM (CBM) | L12: HAULAGE FEE | M12: TTL FOB | N12: TTL FREIGHT | O12: INS | P12: CIF | Q12: % Partner'S MARIN | R12: CIF TO Ergo | S12: IMPORT DUTY RATE | T12: IMPORT DUTY | U12: CBPG RATE | V12: CBPG DUTY | W12: CLEARANCE & DELIVERY | X12: TO WHS COST | Y12: SALES PRICE | Z12: TOTAL G/P | AA12: D2D UNIT PRICE | AB12: D2D UNIT PRICE | AC12: SALES PRICE | AD12: TOTAL G/P | AE12: ALTERNATIVE MARGIN | AF12: 0.05 | AG12: NET GP
AH13: 27000
A14: 1 | D14: 0.43 | E14: 10 | F14: 3576 | G14: =F14*$C$7 -> 3576 | H14: 0.7 | I14: =ROUND(G14*(1-H14),2) -> 1072.8 | J14: =ROUND(E14*I14,2) -> 10728 | K14: =ROUND(E14*D14,2) -> 4.3 | L14: =ROUND(K14*F$7,2) -> 350.02 | M14: =SUM(J14,L14) -> 11078.02 | N14: =ROUND(K14*H$7,2) -> 250 | O14: =ROUND((M14+N14)*$I$9,2) -> 84.96 | P14: =SUM(M14:O14) -> 11412.98 | Q14: 0 | R14: =ROUND(P14/(1-Q14),2) -> 11412.98 | S14: 0.05 | T14: =ROUND(R14*S14,2) -> 570.65 | U14: 0 | V14: =ROUND((T14+R14)*U14,2) -> 0 | W14: =ROUND(K14*R$7,2) -> 500 | X14: =SUM(R14,T14,V14,W14) -> 12483.63 | Y14: =ROUND(X14/(1-T$9),2) -> 20806.05 | Z14: =Y14-X14 -> 8322.42 | AA14: =IF(E14>0,ROUND(Y14/E14,2),"NA") -> 2080.61 | AB14: =AA14 -> 2080.61 | AC14: =ROUND(E14*AB14,2) -> 20806.1 | AD14: =AC14-X14 -> 8322.47 | AE14: =IF(AC14>0,AD14/AC14,"NA") -> 0.40000144 | AF14: =AC14*5%*70% -> 728.2135 | AG14: =AD14-AF14 -> 7594.2565 | AH14: =ROUND(AB14*$AH$13,-3) -> 56176000
E15: =SUM(E14:E14) -> 10 | J15: =SUM(J14:J14) -> 10728 | K15: =SUM(K14:K14) -> 4.3 | L15: =SUM(L14:L14) -> 350.02 | M15: =SUM(M14:M14) -> 11078.02 | N15: =SUM(N14:N14) -> 250 | O15: =SUM(O14:O14) -> 84.96 | P15: =SUM(P14:P14) -> 11412.98 | R15: =SUM(R14:R14) -> 11412.98 | T15: =SUM(T14:T14) -> 570.65 | V15: =SUM(V14:V14) -> 0 | W15: =SUM(W14:W14) -> 500 | X15: =SUM(X14:X14) -> 12483.63 | Y15: =SUM(Y14:Y14) -> 20806.05 | Z15: =SUM(Z14:Z14) -> 8322.42 | AC15: =SUM(AC14:AC14) -> 20806.1 | AD15: =SUM(AD14:AD14) -> 8322.47 | AE15: =SUM(AE14:AE14) -> 0.40000144 | AF15: =SUM(AF14:AF14) -> 728.2135 | AG15: =SUM(AG14:AG14) -> 7594.2565
B16: CROSS CHECK | M16: =SUM(J15,L15) -> 11078.02 | P16: =SUM(M15,N15,O15) -> 11412.98 | R16: =SUM(M15,N15,O15) -> 11412.98 | X16: =SUM(R15,T15,W15,V15) -> 12483.63 | Z16: =Y15-X15 -> 8322.42 | AD16: =AC15-X15 -> 8322.47 | AG16: =AG15/AC15 -> 0.36500144
X17: =X16/E15 -> 1248.363 | Z17: =IF(Y15>0,Z16/Y15,"NA") -> 0.4
P18: =AH13 -> 27000 | T18: =AD16/AC15 -> 0.40000144
H19: Import tax | I19: =T15 -> 570.65 | P19: =I19*$P$18 -> 15407550 | R19: Ergo COST | T19: =SUM(R15,T15,W15,AF15) -> 13211.843
H20: CBPG tax | I20: =V15 -> 0 | P20: =I20*$P$18 -> 0 | R20: Ergo G/P | T20: =AC15-T19 -> 7594.2565
H21: VAT tax | I21: =(R15+I19+I20)*10% -> 1198.363 | P21: =I21*$P$18 -> 32355801 | R21: Ergo MARGIN | T21: =T20/AC15 -> 0.36500144
P22: =SUM(P19:P21) -> 47763351
R23: Ergo TAX | T23: =ROUND(T20*U23,2) -> 1518.85 | U23: 0.2
H24: Consultant fee | P24: 0 | R24: NET G/P | T24: =T20+T22-T23 -> 6075.4065
H25: GP after Consultant fee | P25: =AG15-P24 -> 7594.2565 | R25: NET MARGIN | T25: =T24/AC15 -> 0.29200122
H26: Margin | P26: =P25/AC15 -> 0.36500144

Sheet PC
B1: COSTING SHEET | E1: HAULAGE + CO fee | G1: FREIGHT | Q1: LOCAL | V1: 25000
B2: PROJECT: DIGIWORLD | E2: CONT 20 | F2: 650 | G2: =E2 -> CONT 20 | H2: 650 | I2: =F2+H2+T2 -> 1550 | J2: =800+800+350 -> 1950 | Q2: =G2 -> CONT 20 | R2: =SUM(T2:T7) -> 1010 | S2: Local charge | T2: 250 | U2: =130+50+20+20+40+20 -> 280
E3: FLAT FEE | F3: 0 | G3: FLAT FEE | H3: 0 | Q3: FLAT FEE | R3: 0 | S3: Clearance | T3: 100
B4: DATE: | C4: =NOW() -> 46304.463 | E4: RATE/CBM | F4: 0 | G4: RATE/CBM | H4: 0 | Q4: RATE/CBM | R4: 0 | S4: Load / Install | T4: 280 | U4: =2500000+50000*E15 -> 6450000 | V4: =U4/$V$1 -> 258
E5: TOTAL CBM | F5: =K15 -> 15.8 | G5: TOTAL CBM | H5: =K15 -> 15.8 | Q5: TOTAL CBM | R5: =K15 -> 15.8 | S5: Deliver | T5: 200 | V5: =U5/$V$1 -> 0
B6: CURRENCY: | C6: USD | E6: TOTAL CHARGE | F6: =IF(ROUND(F4*F5,2)>F2,ROUND(F4*F5,2)+F3,F2+F3) -> 650 | G6: TOTAL CHARGE | H6: =IF(ROUND(H4*H5,2)>H2,ROUND(H4*H5,2)+H3,H2+H3) -> 650 | Q6: TOTAL CHARGE | R6: =IF(ROUND(R4*R5,2)>R2,ROUND(R4*R5,2)+R3,R2+R3+(R4*R5)) -> 1010 | S6: Warehouse | T6: 100 | V6: =U6/$V$1 -> 0
B7: EXCHANGE RATE: | C7: 1 | E7: COST/CBM | F7: =IF(F5>0,ROUND(F6/F5,2),0) -> 41.14 | G7: COST/CBM | H7: =IF(H5>0,ROUND(H6/H5,2),0) -> 41.14 | Q7: COST/CBM | R7: =IF(R5>0,ROUND(R6/R5,2),0) -> 63.92 | S7: Prelim | T7: 80
I8: RATE ON CNF | T8: DRIVEN MARGIN
B9: SUPPLIER: | C9: DAEHA | I9: 0.0075 | T9: 0.3
B10: DELIVERY TERMS OF PURCHASES | C10: EXW KOREA
B11: DELIVERY TERMS OF SALES | C11: D2D HCM / HN | I11: =$I$14*$AH$13*2 -> 4505000 | P11: =$I$14*$AH$13*2.5 -> 5631250 | Q11: =$I$14*$AH$13*3 -> 6757500 | Y11: DRIVEN MARGIN METHOD | AB11: DRIVEN MARKET METHOD | AF11: CAF
B12: DESCRIPTION | C12: IMAGE | D12: DIM (CBM) | E12: QTY | F12: FOB UNIT COST | G12: CONVERTED UNIT COST (USD) | H12: % discounted | I12: DISCOUNTED FOB | J12: TTL FOB | K12: TTL DIM (CBM) | L12: HAULAGE FEE | M12: TTL FOB | N12: TTL FREIGHT | O12: INS | P12: CIF | Q12: % Partner'S MARIN | R12: CIF TO Ergo | S12: IMPORT DUTY RATE | T12: IMPORT DUTY | U12: CBPG RATE | V12: CBPG DUTY | W12: CLEARANCE & DELIVERY | X12: TO WHS COST | Y12: SALES PRICE | Z12: TOTAL G/P | AA12: D2D UNIT PRICE | AB12: D2D UNIT PRICE | AC12: SALES PRICE | AD12: TOTAL G/P | AE12: ALTERNATIVE MARGIN | AF12: 0.05 | AG12: NET GP
AH13: 26500
A14: 1 | B14: HUMBLE-HB (BLACK FRAME) Humble Highback Chair in Black Frame; Height Adjustable Armrest; Synchron Mechanism with Seat Depth Adjustment. Nylon Base on Castors | D14: 0.2 | E14: 79 | F14: 85 | G14: =F14*$C$7 -> 85 | H14: 0 | I14: =ROUND(G14*(1-H14),2) -> 85 | J14: =ROUND(E14*I14,2) -> 6715 | K14: =ROUND(E14*D14,2) -> 15.8 | L14: =ROUND(K14*F$7,2) -> 650.01 | M14: =SUM(J14,L14) -> 7365.01 | N14: =ROUND(K14*H$7,2) -> 650.01 | O14: =ROUND((M14+N14)*$I$9,2) -> 60.11 | P14: =SUM(M14:O14) -> 8075.13 | Q14: 0 | R14: =ROUND(P14/(1-Q14),2) -> 8075.13 | S14: 0 | T14: =ROUND(R14*S14,2) -> 0 | U14: 0 | V14: =ROUND((T14+R14)*U14,2) -> 0 | W14: =ROUND(K14*R$7,2) -> 1009.94 | X14: =SUM(R14,T14,V14,W14) -> 9085.07 | Y14: =ROUND(X14/(1-T$9),2) -> 12978.67 | Z14: =Y14-X14 -> 3893.6 | AA14: =IF(E14>0,ROUND(Y14/E14,2),"NA") -> 164.29 | AB14: =AA14 -> 164.29 | AC14: =ROUND(E14*AB14,2) -> 12978.91 | AD14: =AC14-X14 -> 3893.84 | AE14: =IF(AC14>0,AD14/AC14,"NA") -> 0.30001287 | AF14: =AC14*5%*70% -> 454.26185 | AG14: =AD14-AF14 -> 3439.5782 | AH14: =ROUND(AB14*$AH$13,-3) -> 4354000
E15: =SUM(E14:E14) -> 79 | J15: =SUM(J14:J14) -> 6715 | K15: =SUM(K14:K14) -> 15.8 | L15: =SUM(L14:L14) -> 650.01 | M15: =SUM(M14:M14) -> 7365.01 | N15: =SUM(N14:N14) -> 650.01 | O15: =SUM(O14:O14) -> 60.11 | P15: =SUM(P14:P14) -> 8075.13 | R15: =SUM(R14:R14) -> 8075.13 | T15: =SUM(T14:T14) -> 0 | V15: =SUM(V14:V14) -> 0 | W15: =SUM(W14:W14) -> 1009.94 | X15: =SUM(X14:X14) -> 9085.07 | Y15: =SUM(Y14:Y14) -> 12978.67 | Z15: =SUM(Z14:Z14) -> 3893.6 | AC15: =SUM(AC14:AC14) -> 12978.91 | AD15: =SUM(AD14:AD14) -> 3893.84 | AE15: =SUM(AE14:AE14) -> 0.30001287 | AF15: =SUM(AF14:AF14) -> 454.26185 | AG15: =SUM(AG14:AG14) -> 3439.5782
B16: CROSS CHECK | M16: =SUM(J15,L15) -> 7365.01 | P16: =SUM(M15,N15,O15) -> 8075.13 | R16: =SUM(M15,N15,O15) -> 8075.13 | X16: =SUM(R15,T15,W15,V15) -> 9085.07 | Z16: =Y15-X15 -> 3893.6 | AD16: =AC15-X15 -> 3893.84 | AG16: =AG15/AC15 -> 0.26501287
X17: =X16/E15 -> 115.00089 | Z17: =IF(Y15>0,Z16/Y15,"NA") -> 0.29999992
P18: =AH13 -> 26500 | T18: =AD16/AC15 -> 0.30001287
H19: Import tax | I19: =T15 -> 0 | P19: =I19*$P$18 -> 0 | R19: Ergo COST | T19: =SUM(R15,T15,W15,AF15) -> 9539.3319
H20: CBPG tax | I20: =V15 -> 0 | P20: =I20*$P$18 -> 0 | R20: Ergo G/P | T20: =AC15-T19 -> 3439.5781
H21: VAT tax | I21: =(R15+I19+I20)*10% -> 807.513 | P21: =I21*$P$18 -> 21399094 | R21: Ergo MARGIN | T21: =T20/AC15 -> 0.26501287
P22: =SUM(P19:P21) -> 21399094
R23: Ergo TAX | T23: =ROUND(T20*U23,2) -> 687.92 | U23: 0.2
H24: Consultant fee | P24: 0 | R24: NET G/P | T24: =T20+T22-T23 -> 2751.6581
H25: GP after Consultant fee | P25: =AG15-P24 -> 3439.5782 | R25: NET MARGIN | T25: =T24/AC15 -> 0.21200996
H26: Margin | P26: =P25/AC15 -> 0.26501287

Sheet HAD
B1: COSTING SHEET | E1: HAULAGE + CO fee | G1: FREIGHT | Q1: LOCAL | V1: 25000
B2: PROJECT: ABC | D2: 1.3 | E2: LCL | F2: 400 | G2: =E2 -> LCL | H2: =100 -> 100 | I2: =F2+H2+T2 -> 650 | J2: =800+800+350 -> 1950 | Q2: =G2 -> LCL | R2: =SUM(T2:T7) -> 1410 | S2: Local charge | T2: 150 | U2: =(5+15+5)*F5+20+30 -> 225 | V2: =U2*130% -> 292.5
E3: FLAT FEE | F3: 0 | G3: FLAT FEE | H3: 0 | Q3: FLAT FEE | R3: 0 | S3: Clearance | T3: 80
B4: DATE: | C4: =NOW() -> 46304.463 | E4: RATE/CBM | F4: 0 | G4: RATE/CBM | H4: 0 | Q4: RATE/CBM | R4: 0 | S4: Load / Install | T4: 1000 | U4: =1500000+600000*E15 -> 22500000 | V4: =U4/$V$1 -> 900
E5: TOTAL CBM | F5: =K15 -> 7 | G5: TOTAL CBM | H5: =K15 -> 7 | Q5: TOTAL CBM | R5: =K15 -> 7 | S5: Deliver | T5: 100
B6: CURRENCY: | C6: USD | E6: TOTAL CHARGE | F6: =IF(ROUND(F4*F5,2)>F2,ROUND(F4*F5,2)+F3,F2+F3) -> 400 | G6: TOTAL CHARGE | H6: =IF(ROUND(H4*H5,2)>H2,ROUND(H4*H5,2)+H3,H2+H3) -> 100 | Q6: TOTAL CHARGE | R6: =IF(ROUND(R4*R5,2)>R2,ROUND(R4*R5,2)+R3,R2+R3+(R4*R5)) -> 1410 | S6: Warehouse | T6: 50
B7: EXCHANGE RATE: | C7: 1 | E7: COST/CBM | F7: =IF(F5>0,ROUND(F6/F5,2),0) -> 57.14 | G7: COST/CBM | H7: =IF(H5>0,ROUND(H6/H5,2),0) -> 14.29 | Q7: COST/CBM | R7: =IF(R5>0,ROUND(R6/R5,2),0) -> 201.43 | S7: Prelim | T7: 30
I8: RATE ON CNF | T8: DRIVEN MARGIN
B9: SUPPLIER: | C9: HUMANSCALE | I9: 0.0075 | T9: 0.25
B10: DELIVERY TERMS OF PURCHASES | C10: EXW china
B11: DELIVERY TERMS OF SALES | C11: D2D HCM / HN | I11: =$I$14*$AH$13*2 -> 40258800 | P11: =$I$14*$AH$13*2.5 -> 50323500 | Q11: =$I$14*$AH$13*3 -> 60388200 | Y11: DRIVEN MARGIN METHOD | AB11: DRIVEN MARKET METHOD | AF11: CAF
B12: DESCRIPTION | C12: IMAGE | D12: DIM (CBM) | E12: QTY | F12: FOB UNIT COST | G12: CONVERTED UNIT COST (USD) | H12: % discounted | I12: DISCOUNTED FOB | J12: TTL FOB | K12: TTL DIM (CBM) | L12: HAULAGE FEE | M12: TTL FOB | N12: TTL FREIGHT | O12: INS | P12: CIF | Q12: % Partner'S MARIN | R12: CIF TO Ergo | S12: IMPORT DUTY RATE | T12: IMPORT DUTY | U12: CBPG RATE | V12: CBPG DUTY | W12: CLEARANCE & DELIVERY | X12: TO WHS COST | Y12: SALES PRICE | Z12: TOTAL G/P | AA12: D2D UNIT PRICE | AB12: D2D UNIT PRICE | AC12: SALES PRICE | AD12: TOTAL G/P | AE12: ALTERNATIVE MARGIN | AF12: 0.05 | AG12: NET GP
AH13: 26500 | AI13: TABLE TOP | AJ13: CABLE TRAY | AK13: CABLE SNAKE | AL13: PANEL | AM13: OTE | AN13: SUM
A14: 1 | B14: ISOR42186EF (Cluster of 2) H-Frame with eFloat Go 2.0 Frame: White Shared lower cable tray Clamp for panel Accommodates worksurfaces 1220 - 1830mm Simple installation Digital programmable handset with USD charging | D14: 0.2 | E14: 35 | F14: 1899 | G14: =F14*$C$7 -> 1899 | H14: 0.6 | I14: =ROUND(G14*(1-H14),2) -> 759.6 | J14: =ROUND(E14*I14,2) -> 26586 | K14: =ROUND(E14*D14,2) -> 7 | L14: =ROUND(K14*F$7,2) -> 399.98 | M14: =SUM(J14,L14) -> 26985.98 | N14: =ROUND(K14*H$7,2) -> 100.03 | O14: =ROUND((M14+N14)*$I$9,2) -> 203.15 | P14: =SUM(M14:O14) -> 27289.16 | Q14: 0 | R14: =ROUND(P14/(1-Q14),2) -> 27289.16 | S14: 0 | T14: =ROUND(R14*S14,2) -> 0 | U14: 0 | V14: =ROUND((T14+R14)*U14,2) -> 0 | W14: =ROUND(K14*R$7,2) -> 1410.01 | X14: =SUM(R14,T14,V14,W14) -> 28699.17 | Y14: =ROUND(X14/(1-T$9),2) -> 38265.56 | Z14: =Y14-X14 -> 9566.39 | AA14: =IF(E14>0,ROUND(Y14/E14,2),"NA") -> 1093.3 | AB14: =AA14 -> 1093.3 | AC14: =ROUND(E14*AB14,2) -> 38265.5 | AD14: =AC14-X14 -> 9566.33 | AE14: =IF(AC14>0,AD14/AC14,"NA") -> 0.24999882 | AF14: =AC14*5%*70% -> 1339.2925 | AG14: =AD14-AF14 -> 8227.0375 | AH14: =ROUND(AB14*$AH$13,-3) -> 28972000 | AI14: ='HAD''s'!M13*2 -> 3282000 | AJ14: ='HAD''s'!M14*2 -> 1642000 | AK14: ='Cable Snake'!AH14*2 -> 508000 | AL14: ='HAD''s'!M17 -> 1010000 | AM14: =#REF! -> #REF! | AN14: =SUM(AH14:AM14) -> #REF! | AO14: =AN14/2 -> #REF!
E15: =SUM(E14:E14) -> 35 | J15: =SUM(J14:J14) -> 26586 | K15: =SUM(K14:K14) -> 7 | L15: =SUM(L14:L14) -> 399.98 | M15: =SUM(M14:M14) -> 26985.98 | N15: =SUM(N14:N14) -> 100.03 | O15: =SUM(O14:O14) -> 203.15 | P15: =SUM(P14:P14) -> 27289.16 | R15: =SUM(R14:R14) -> 27289.16 | T15: =SUM(T14:T14) -> 0 | V15: =SUM(V14:V14) -> 0 | W15: =SUM(W14:W14) -> 1410.01 | X15: =SUM(X14:X14) -> 28699.17 | Y15: =SUM(Y14:Y14) -> 38265.56 | Z15: =SUM(Z14:Z14) -> 9566.39 | AC15: =SUM(AC14:AC14) -> 38265.5 | AD15: =SUM(AD14:AD14) -> 9566.33 | AE15: =SUM(AE14:AE14) -> 0.24999882 | AF15: =SUM(AF14:AF14) -> 1339.2925 | AG15: =SUM(AG14:AG14) -> 8227.0375
B16: CROSS CHECK | M16: =SUM(J15,L15) -> 26985.98 | P16: =SUM(M15,N15,O15) -> 27289.16 | R16: =SUM(M15,N15,O15) -> 27289.16 | X16: =SUM(R15,T15,W15,V15) -> 28699.17 | Z16: =Y15-X15 -> 9566.39 | AD16: =AC15-X15 -> 9566.33 | AG16: =AG15/AC15 -> 0.21499882
X17: =X16/E15 -> 819.97629 | Z17: =IF(Y15>0,Z16/Y15,"NA") -> 0.25
P18: =AH13 -> 26500 | T18: =AD16/AC15 -> 0.24999882
H19: Import tax | I19: =T15 -> 0 | P19: =I19*$P$18 -> 0 | R19: Ergo COST | T19: =SUM(R15,T15,W15,AF15) -> 30038.462
H20: CBPG tax | I20: =V15 -> 0 | P20: =I20*$P$18 -> 0 | R20: Ergo G/P | T20: =AC15-T19 -> 8227.0375
H21: VAT tax | I21: =(R15+I19+I20)*10% -> 2728.916 | P21: =I21*$P$18 -> 72316274 | R21: Ergo MARGIN | T21: =T20/AC15 -> 0.21499882
P22: =SUM(P19:P21) -> 72316274
R23: Ergo TAX | T23: =ROUND(T20*U23,2) -> 1645.41 | U23: 0.2
H24: Consultant fee | P24: 0 | R24: NET G/P | T24: =T20+T22-T23 -> 6581.6275
H25: GP after Consultant fee | P25: =AG15-P24 -> 8227.0375 | R25: NET MARGIN | T25: =T24/AC15 -> 0.17199899
H26: Margin | P26: =P25/AC15 -> 0.21499882

Sheet HAD's
B1: FCL COSTING SHEET
B2: PROJECT: MSD HCM P2
B4: DATE: | D4: Delivery: | E4: 2000000 | F4: =E4+E5 -> 2000000
B5: PRICE LIST: | D5: Installation: | E5: 0
D7: GP | E7: 0.2
B9: SUPPLIER: | C9: TAV
B10: DELIVERY TERMS OF SALES | C10: D2D HCMC
B11: DESCRIPTION | C11: STYLE NO. | D11: QTY | E11: UNIT PRICE (VND) | F11: % discounted | G11: AFTER DIS UNIT PRICE (VND) | H11: AFTER DIS TOTAL PRICE (VND) | I11: DELIVERY & INSTALL FEE | J11: UNIT COST | K11: TOTAL COST | L11: D2D UNIT PRICE | M11: D2D UNIT PRICE | N11: TOTAL FOR SALES | O11: ALTERNATIVE MARGIN
A13: 1 | B13: Table top MFC 25mm 1500x700x25mm scallop for cable management | C13: TAV | D13: =HAD!E14*2 -> 70 | E13: 1300000 | F13: 0 | G13: =E13*(100%-F13) -> 1300000 | H13: =G13*D13 -> 91000000 | I13: =ROUND($F$4/$H$18*H13/D13,0) -> 12897 | J13: =(I13+G13) -> 1312897 | K13: =J13*D13 -> 91902790 | L13: =J13/(1-$E$7) -> 1641121.2 | M13: =ROUND(L13,-3) -> 1641000 | N13: =M13*D13 -> 114870000 | O13: =(N13-K13)/N13 -> 0.19994089
A14: 2 | B14: Cable Tray Customized dimension | C14: Toàn Thắng | D14: =D13 -> 70 | E14: 650000 | F14: 0 | G14: =E14*(100%-F14) -> 650000 | H14: =G14*D14 -> 45500000 | I14: =ROUND($F$4/$H$18*H14/D14,0) -> 6448 | J14: =(I14+G14) -> 656448 | K14: =J14*D14 -> 45951360 | L14: =J14/(1-$E$7) -> 820560 | M14: =ROUND(L14,-3) -> 821000 | N14: =M14*D14 -> 57470000 | O14: =(N14-K14)/N14 -> 0.20042875
A15: 3 | B15: Cable Snake | C15: Thuý Nhi/ Ergolife / Nhập | D15: =D13 -> 70 | E15: 330000 | F15: 0 | G15: =E15*(100%-F15) -> 330000 | H15: =G15*D15 -> 23100000 | I15: =ROUND($F$4/$H$18*H15/D15,0) -> 3274 | J15: =(I15+G15) -> 333274 | K15: =J15*D15 -> 23329180 | L15: =J15/(1-$E$7) -> 416592.5 | M15: =ROUND(L15,-3) -> 417000 | N15: =M15*D15 -> 29190000 | O15: =(N15-K15)/N15 -> 0.20078177
A16: 4 | B16: Flipper | C16: Thuý Nhi/ Ergolife / Nhập | D16: =D14 -> 70 | E16: 200000 | F16: 0 | G16: =E16*(100%-F16) -> 200000 | H16: =G16*D16 -> 14000000 | I16: =ROUND($F$4/$H$18*H16/D16,0) -> 1984 | J16: =(I16+G16) -> 201984 | K16: =J16*D16 -> 14138880 | L16: =J16/(1-$E$7) -> 252480 | M16: =ROUND(L16,-3) -> 252000 | N16: =M16*D16 -> 17640000 | O16: =(N16-K16)/N16 -> 0.19847619
A17: 5 | B17: Shared Panel (TAV) Vách ngăn okal bọc nỉ không ghim 1500x760x20 | D17: =HAD!E14 -> 35 | E17: 800000 | F17: 0 | G17: =E17*(100%-F17) -> 800000 | H17: =G17*D17 -> 28000000 | I17: =ROUND($F$4/$H$18*H17/D17,0) -> 7937 | J17: =(I17+G17) -> 807937 | K17: =J17*D17 -> 28277795 | L17: =J17/(1-$E$7) -> 1009921.2 | M17: =ROUND(L17,-3) -> 1010000 | N17: =M17*D17 -> 35350000 | O17: =(N17-K17)/N17 -> 0.20006238
B18: TOTAL | D18: =SUM(D13:D17) -> 315 | H18: =SUM(H13:H17) -> 201600000 | K18: =SUM(K13:K17) -> 203600005 | N18: =SUM(N13:N17) -> 254520000 | O18: =(N18-K18)/N18 -> 0.20006284

Sheet Cable Snake
B1: COSTING SHEET | E1: HAULAGE + CO fee | G1: FREIGHT | Q1: LOCAL | V1: 25000
B2: PROJECT: MARVELL | E2: LCL | F2: 300 | G2: =E2 -> LCL | H2: =50 -> 50 | I2: =F2+H2+T2 -> 450 | J2: =800+800+350 -> 1950 | Q2: =G2 -> LCL | R2: =SUM(T2:T7) -> 320 | S2: Local charge | T2: 100 | U2: =(5+15+5)*1+30+20 -> 75
E3: FLAT FEE | F3: 0 | G3: FLAT FEE | H3: 0 | Q3: FLAT FEE | R3: 0 | S3: Clearance | T3: 100
B4: DATE: | C4: =NOW() -> 46304.463 | E4: RATE/CBM | F4: 0 | G4: RATE/CBM | H4: 0 | Q4: RATE/CBM | R4: 0 | S4: Load / Install
E5: TOTAL CBM | F5: =K15 -> 0.9 | G5: TOTAL CBM | H5: =K15 -> 0.9 | Q5: TOTAL CBM | R5: =K15 -> 0.9 | S5: Deliver | T5: 70
B6: CURRENCY: | C6: USD | E6: TOTAL CHARGE | F6: =IF(ROUND(F4*F5,2)>F2,ROUND(F4*F5,2)+F3,F2+F3) -> 300 | G6: TOTAL CHARGE | H6: =IF(ROUND(H4*H5,2)>H2,ROUND(H4*H5,2)+H3,H2+H3) -> 50 | Q6: TOTAL CHARGE | R6: =IF(ROUND(R4*R5,2)>R2,ROUND(R4*R5,2)+R3,R2+R3+(R4*R5)) -> 320 | S6: Warehouse | T6: 30
B7: EXCHANGE RATE: | C7: 1 | E7: COST/CBM | F7: =IF(F5>0,ROUND(F6/F5,2),0) -> 333.33 | G7: COST/CBM | H7: =IF(H5>0,ROUND(H6/H5,2),0) -> 55.56 | Q7: COST/CBM | R7: =IF(R5>0,ROUND(R6/R5,2),0) -> 355.56 | S7: Prelim | T7: 20
I8: RATE ON CNF | T8: DRIVEN MARGIN
B9: SUPPLIER: | C9: LUMI | I9: 0.0075 | T9: 0.2
B10: DELIVERY TERMS OF PURCHASES | C10: EXW china
B11: DELIVERY TERMS OF SALES | C11: D2D HCM / HN | I11: =$I$14*$AH$13*2 -> 228800 | P11: =$I$14*$AH$13*2.5 -> 286000 | Q11: =$I$14*$AH$13*3 -> 343200 | Y11: DRIVEN MARGIN METHOD | AB11: DRIVEN MARKET METHOD | AF11: CAF
B12: DESCRIPTION | C12: IMAGE | D12: DIM (CBM) | E12: QTY | F12: FOB UNIT COST | G12: CONVERTED UNIT COST (USD) | H12: % discounted | I12: DISCOUNTED FOB | J12: TTL FOB | K12: TTL DIM (CBM) | L12: HAULAGE FEE | M12: TTL FOB | N12: TTL FREIGHT | O12: INS | P12: CIF | Q12: % Partner'S MARIN | R12: CIF TO Ergo | S12: IMPORT DUTY RATE | T12: IMPORT DUTY | U12: CBPG RATE | V12: CBPG DUTY | W12: CLEARANCE & DELIVERY | X12: TO WHS COST | Y12: SALES PRICE | Z12: TOTAL G/P | AA12: D2D UNIT PRICE | AB12: D2D UNIT PRICE | AC12: SALES PRICE | AD12: TOTAL G/P | AE12: ALTERNATIVE MARGIN | AF12: 0.05 | AG12: NET GP
AH13: 26000
A14: 1 | B14: CC10-15 Cost-Effective Screw-Mounted Cable Management Spine Material: ABS,Steel Surface Finish: Powder Coating Dimensions: 99.4x99.4x1297mm (3.9"x3.9"x51.1") Joints: 35 Installation: Screw Fixation Color: White,Black,Silver | D14: =F18 -> 0.0045038889 | E14: 200 | F14: 4.4 | G14: =F14*$C$7 -> 4.4 | H14: 0 | I14: =ROUND(G14*(1-H14),2) -> 4.4 | J14: =ROUND(E14*I14,2) -> 880 | K14: =ROUND(E14*D14,2) -> 0.9 | L14: =ROUND(K14*F$7,2) -> 300 | M14: =SUM(J14,L14) -> 1180 | N14: =ROUND(K14*H$7,2) -> 50 | O14: =ROUND((M14+N14)*$I$9,2) -> 9.23 | P14: =SUM(M14:O14) -> 1239.23 | Q14: 0 | R14: =ROUND(P14/(1-Q14),2) -> 1239.23 | S14: 0 | T14: =ROUND(R14*S14,2) -> 0 | U14: 0 | V14: =ROUND((T14+R14)*U14,2) -> 0 | W14: =ROUND(K14*R$7,2) -> 320 | X14: =SUM(R14,T14,V14,W14) -> 1559.23 | Y14: =ROUND(X14/(1-T$9),2) -> 1949.04 | Z14: =Y14-X14 -> 389.81 | AA14: =IF(E14>0,ROUND(Y14/E14,2),"NA") -> 9.75 | AB14: =AA14 -> 9.75 | AC14: =ROUND(E14*AB14,2) -> 1950 | AD14: =AC14-X14 -> 390.77 | AE14: =IF(AC14>0,AD14/AC14,"NA") -> 0.20039487 | AF14: =AC14*5%*70% -> 68.25 | AG14: =AD14-AF14 -> 322.52 | AH14: =ROUND(AB14*$AH$13,-3) -> 254000
E15: =SUM(E14:E14) -> 200 | J15: =SUM(J14:J14) -> 880 | K15: =SUM(K14:K14) -> 0.9 | L15: =SUM(L14:L14) -> 300 | M15: =SUM(M14:M14) -> 1180 | N15: =SUM(N14:N14) -> 50 | O15: =SUM(O14:O14) -> 9.23 | P15: =SUM(P14:P14) -> 1239.23 | R15: =SUM(R14:R14) -> 1239.23 | T15: =SUM(T14:T14) -> 0 | V15: =SUM(V14:V14) -> 0 | W15: =SUM(W14:W14) -> 320 | X15: =SUM(X14:X14) -> 1559.23 | Y15: =SUM(Y14:Y14) -> 1949.04 | Z15: =SUM(Z14:Z14) -> 389.81 | AC15: =SUM(AC14:AC14) -> 1950 | AD15: =SUM(AD14:AD14) -> 390.77 | AE15: =SUM(AE14:AE14) -> 0.20039487 | AF15: =SUM(AF14:AF14) -> 68.25 | AG15: =SUM(AG14:AG14) -> 322.52
B16: CROSS CHECK | M16: =SUM(J15,L15) -> 1180 | P16: =SUM(M15,N15,O15) -> 1239.23 | R16: =SUM(M15,N15,O15) -> 1239.23 | X16: =SUM(R15,T15,W15,V15) -> 1559.23 | Z16: =Y15-X15 -> 389.81 | AD16: =AC15-X15 -> 390.77 | AG16: =AG15/AC15 -> 0.16539487
X17: =X16/E15 -> 7.79615 | Z17: =IF(Y15>0,Z16/Y15,"NA") -> 0.20000103
B18: https://www.lumi.cn/en/lumi-ergo/office-accessories/cable-management/cc10-15 | E18: =0.605*0.4*0.335 -> 0.08107 | F18: =E18/18 -> 0.0045038889 | P18: =AH13 -> 26000 | T18: =AD16/AC15 -> 0.20039487
H19: Import tax | I19: =T15 -> 0 | P19: =I19*$P$18 -> 0 | R19: Ergo COST | T19: =SUM(R15,T15,W15,AF15) -> 1627.48
H20: CBPG tax | I20: =V15 -> 0 | P20: =I20*$P$18 -> 0 | R20: Ergo G/P | T20: =AC15-T19 -> 322.52
H21: VAT tax | I21: =(R15+I19+I20)*10% -> 123.923 | P21: =I21*$P$18 -> 3221998 | R21: Ergo MARGIN | T21: =T20/AC15 -> 0.16539487
P22: =SUM(P19:P21) -> 3221998
R23: Ergo TAX | T23: =ROUND(T20*U23,2) -> 64.5 | U23: 0.2
H24: Consultant fee | P24: 0 | R24: NET G/P | T24: =T20+T22-T23 -> 258.02
H25: GP after Consultant fee | P25: =AG15-P24 -> 322.52 | R25: NET MARGIN | T25: =T24/AC15 -> 0.13231795
H26: Margin | P26: =P25/AC15 -> 0.16539487

Sheet Note
A2: CÁC LƯU Ý KHI LÀM COSTING
B4: 1. Lưu ý thời điểm bàn giao dự án để ước tính tỷ giá, chi phí đội giá … 2. Cần mua bảo hiểm cho các chuyến tàu giá trị cao / thời gian vận chuyển dài 3. Costing cho dự án ở Hà Nội nên để x1.5 lần HCM 4. Để ý địa điểm giao hàng, ở tỉnh, đi xa hơn ngoài nội thành ... để tính chi phí delivery cho phù hợp 5. Dự trù các phương án xấu nhất có thể xảy ra: giá tăng, kiểm hóa, chi hải quan, chi ngoài bảo vệ, ba gác, chi phí công trình, hư hỏng …
A6: STT | B6: STEP | C6: NOTE | D6: LINK
A7: 1 | B7: Pricelist | C7: - HS website (APAC) - Partners trên server - PO cũ - Hỏi shipper (nếu sản phẩm lạ / pricelist-PO cũ hơn 6 tháng) | D7: Z:\5. Partners
A8: 2 | B8: Xin báo giá Shipper mới | C8: - Sản phẩm - Số lượng - Giá EXW (đơn vị tiền) - Leadtime - Bảo hành - Nước sản xuất - Có làm đc CO không
A9: 3 | B9: Discount | C9: - HS: 65-73% - Framery: 60% - Grado: 55% Contract, 50% Living trên bảng pricelist, báo giá lẻ là giá net - Krede: pricelist là giá net - Benel: pricelist là giá net - Wilkhahn: hỏi giá case by case - Bossdesign: 30% - HNI-Lamex: 50% - Segis: 60% - Schiavello: hỏi giá case by case% - Flokk: 60% - Shipper lạ: recheck | D9: - Cinto: 65% - Standard: 70% - Applied cao hơn: xin tuỳ dự án, số lượng
A10: 4 | B10: CBM | C10: Standard - Ghế văn phòng: 0.25 - 0.3 - Bàn: (HxWxD)/3 - Phụ kiện: 0.1
C11: Chính xác hơn: - PO cũ - Xem số lượng / container trên báo giá - Check với shipper | D11: https://tfwspacevn.sharepoint.com/:x:/r/sites/DATA84/_layouts/15/Doc.aspx?sourcedoc=%7BAA30BE71-B5C6-4376-A981-ED8F505D1CC8%7D&file=Packing%20Dimension.xlsx&action=default&mobileredirect=true
A12: 5 | B12: Import tax | C12: China: CO Form E - Ghế xoay + nâng hạ: 5% - Ghế khác: 0% - Bàn: 5% - Phụ kiện: 0% - Phonebooth: 5% | D12: https://tfwspacevn.sharepoint.com/:x:/r/sites/DATA84/_layouts/15/Doc.aspx?sourcedoc=%7B80AF788E-EBAB-477E-99B1-17DFA39AFCD9%7D&file=FWD%20Updating%20Quotation.xlsx&action=default&mobileredirect=true
C13: Malay: CO Form D - Toàn bộ sản phẩm: 0%
C14: Australia: AANZ - Tùy sản phẩm: 0-7%
C15: EU: REX code - Tùy sản phẩm: 0-12.5%
C16: 25% - Khụ vực khác (US, Singapore…) - Framery SING (Phonebooth): 10% - Không có CO
C17: - PO cũ - Check với FWD khai hải quan
A18: 6 | B18: CBPG tax (China only) | C18: Ghế: 21.4% - Chiều cao mặt đất lên mặt ngồi > 450mm - Chân không phải là chân nhôm | D18: chân nhựa / chân chrome: bị chân aluminum (nhôm): không bị chiều cao mặt ngồi: <450mm sofa / ghế training: không bị, stool cao quầy bar > 670mm: không bị >450mm: đa số là ghế làm việc: bị
C19: Bàn: 35.2% - Trừ bàn tròn - Trừ bàn coffee KT nhỏ, hoặc bàn họp KT >3300m - Trừ phụ kiện bàn
A20: 7 | B20: Check thêm với shipper | C20: Chi phí CO (if any) - Wilkhahn: $150 - Krede: $130 (agent mình làm) - Wintech: $85 - Milliken: $100
C21: - Leadtime (nếu sản phẩm lạ)
A22: 8 | B22: Shipping method | C22: - LCL: 0-12 cbm - 20ft: 12-24 cbm - 40ft: 25 - 44 cbm (max 33) - 40ft HC: 46 cbm - 45ft HC: 51 cbm
A23: 9 | B23: Logistics cost | C23: - File Tổng hợp chi phí Logistics - Folder Báo giá FWD - Hỏi báo giá FWD (nếu tuyến lạ) | D23: Z:\1. Ergo\4. SA Team\8. Logistic Z:\1.SERVER\1. Ergo\4. SA Team\8. Logistic\Báo giá FWD
C24: EXW Tham khảo (Asia) - LCL: 250 - 550 - 20ft: 800 - 1300 - 40ft: 1000 - 1500 | D24: Theo thứ tự giá tăng dần: - China - Malay - Korea - Singapore - Australia - EU | F24: CBM
C25: Freight Tham khảo (Asia) - LCL: 50 * CBM - 20ft: 800 - 1300 - 40ft: 1000 - 1500 | F25: 1-12 | G25: 10-12
C26: Local Charge - LCL: 150 - 20ft: 350 - 40ft: 550 | F26: 300-350 | G26: 350-450-550
C27: Customs Clearance - 1 tờ khai: 80 usd - Kiểm hóa / Luồng đỏ: phát sinh chi phí
A28: 10 | B28: Delivery cost (Cát Lái - HCM) | C28: Loading - LCL: 500 - 1500 - 20ft: 2500 - 40ft: 3500
C29: Trucking cont - 20ft: 350 - 40ft: 550
C30: Trucking cont ra site / chuyến - 20ft: 3.200.000 tr - 40ft: 3.800.000 tr
C31: Trucking tải - LCL: 20-40 ghế / tải tuỷ kích thước ghế - 20ft: 4-5 tải - 40ft: 8-10 tải Chi phí 1 tải: 850.000 - 1.200.000 - 1.800.000 / xe tuỳ kích
C32: Trucking ba gác xuống hầm - 1 chuyến: 6-8 ghế Chi phí 1 chuyến: 200.000
C33: Warehouse cảng - LCL: free 5 days - Cont: free 7-14 days tùy vào hãng tàu book - LCL: 20 - 100 usd - 20ft: 100 - 150 usd - 40ft: 150 - 200 usd Chi phí theo CBM: 8.000 / CBM / ngày Loading: 55.000-70.000 / CBM / 2 lần in out
A34: 11 | B34: Loading & Installation | C34: Xem bảng Pricelist Giá ở HN: x1.5-2 | D34: https://tfwspacevn.sharepoint.com/:x:/r/sites/DATA84/_layouts/15/Doc.aspx?sourcedoc=%7B1CAFDA79-CF92-481C-B951-935B03043AFA%7D&file=3.%20Installation%20Price%20list%20(update%202025).xlsx&action=default&mobileredirect=true
